<Persons>
            <Person ID="1">
                <name>周星星</name>
                <age>20</age>
            </Person>
            <Person ID="2">
                <name>白晶晶</name>
                <age>18</age>
    <level>10</level>

            </Person>
</Persons>

      <!--  -&#45;&#45;&#45;&#45;&#45;&#45;&#45;&#45;&#45;&#45;&#45;&#45;&#45;&#45;&#45;&#45;&#45;&#45;&#45;&#45;

        本文来自 NickWei9999 的CSDN 博客 ，全文地址请点击：https://blog.csdn.net/u010984552/article/details/52910966?utm_source=copy -->